edwh_git_plugin/__about__.py
edwh_git_plugin/__init__.py
edwh_git_plugin/git_plugin.py
edwh_git_plugin-0.1.0.dist-info/METADATA
edwh_git_plugin-0.1.0.dist-info/WHEEL
edwh_git_plugin-0.1.0.dist-info/entry_points.txt
edwh_git_plugin-0.1.0.dist-info/licenses/LICENSE.txt
edwh_git_plugin-0.1.0.dist-info/RECORD
